{
  "spectra": [
    {
      "id": "e136",
      "title": "New Spectrum 2",
      "datasets": [
        {
          "id": "d1731854006148",
          "name": "TEST",
          "data": [
            {
              "x": 1723.55,
              "y": 46229.3
            },
            {
              "x": 1722.57,
              "y": 47005.9
            },
            {
              "x": 1721.59,
              "y": 47159.5
            },
            {
              "x": 1720.61,
              "y": 47011.8
            },
            {
              "x": 1719.63,
              "y": 46986.6
            },
            {
              "x": 1718.65,
              "y": 47247.4
            },
            {
              "x": 1717.67,
              "y": 47666.2
            },
            {
              "x": 1716.69,
              "y": 47794
            },
            {
              "x": 1715.71,
              "y": 47725.4
            },
            {
              "x": 1714.73,
              "y": 48368.2
            },
            {
              "x": 1713.75,
              "y": 47914.5
            },
            {
              "x": 1712.77,
              "y": 48332.8
            },
            {
              "x": 1711.79,
              "y": 48388.9
            },
            {
              "x": 1710.81,
              "y": 48661.7
            },
            {
              "x": 1709.83,
              "y": 48664.2
            },
            {
              "x": 1708.85,
              "y": 49076.9
            },
            {
              "x": 1707.86,
              "y": 48786.5
            },
            {
              "x": 1706.88,
              "y": 49535
            },
            {
              "x": 1705.9,
              "y": 49850.5
            },
            {
              "x": 1704.92,
              "y": 49898.6
            },
            {
              "x": 1703.93,
              "y": 50246.9
            },
            {
              "x": 1702.95,
              "y": 50701.9
            },
            {
              "x": 1701.97,
              "y": 51075.4
            },
            {
              "x": 1700.99,
              "y": 51161.3
            }
          ],
          "color": "#60a5fa"
        },
        {
          "id": "d1731854006150",
          "name": "TEST-3",
          "data": [
            {
              "x": 1723.55,
              "y": 408976
            },
            {
              "x": 1722.57,
              "y": 414023
            },
            {
              "x": 1721.59,
              "y": 415058
            },
            {
              "x": 1720.61,
              "y": 418030
            },
            {
              "x": 1719.63,
              "y": 417935
            },
            {
              "x": 1718.65,
              "y": 416510
            },
            {
              "x": 1717.67,
              "y": 418753
            },
            {
              "x": 1716.69,
              "y": 417620
            },
            {
              "x": 1715.71,
              "y": 419099
            },
            {
              "x": 1714.73,
              "y": 420047
            },
            {
              "x": 1713.75,
              "y": 420673
            },
            {
              "x": 1712.77,
              "y": 420047
            },
            {
              "x": 1711.79,
              "y": 421728
            },
            {
              "x": 1710.81,
              "y": 421854
            },
            {
              "x": 1709.83,
              "y": 422388
            },
            {
              "x": 1708.85,
              "y": 421752
            },
            {
              "x": 1707.86,
              "y": 423446
            },
            {
              "x": 1706.88,
              "y": 423635
            },
            {
              "x": 1705.9,
              "y": 425092
            },
            {
              "x": 1704.92,
              "y": 425543
            },
            {
              "x": 1703.93,
              "y": 426645
            },
            {
              "x": 1702.95,
              "y": 426729
            },
            {
              "x": 1701.97,
              "y": 426746
            },
            {
              "x": 1700.99,
              "y": 427984
            },
            {
              "x": 1700,
              "y": 429070
            },
            {
              "x": 1699.02,
              "y": 428784
            },
            {
              "x": 1698.04,
              "y": 428733
            },
            {
              "x": 1697.05,
              "y": 430623
            },
            {
              "x": 1696.07,
              "y": 431739
            }
          ],
          "color": "#fbbf24"
        },
        {
          "id": "d1731862758669",
          "name": "TEST-2",
          "data": [
            {
              "x": 1723.55,
              "y": 46229.3
            },
            {
              "x": 1722.57,
              "y": 47005.9
            },
            {
              "x": 1721.59,
              "y": 47159.5
            },
            {
              "x": 1720.61,
              "y": 47011.8
            },
            {
              "x": 1719.63,
              "y": 46986.6
            },
            {
              "x": 1718.65,
              "y": 47247.4
            },
            {
              "x": 1717.67,
              "y": 47666.2
            },
            {
              "x": 1716.69,
              "y": 47794
            },
            {
              "x": 1715.71,
              "y": 47725.4
            },
            {
              "x": 1714.73,
              "y": 48368.2
            },
            {
              "x": 1713.75,
              "y": 47914.5
            },
            {
              "x": 1712.77,
              "y": 48332.8
            },
            {
              "x": 1711.79,
              "y": 48388.9
            },
            {
              "x": 1710.81,
              "y": 48661.7
            },
            {
              "x": 1709.83,
              "y": 48664.2
            },
            {
              "x": 1708.85,
              "y": 49076.9
            },
            {
              "x": 1707.86,
              "y": 48786.5
            },
            {
              "x": 1706.88,
              "y": 49535
            },
            {
              "x": 1705.9,
              "y": 49850.5
            },
            {
              "x": 1704.92,
              "y": 49898.6
            },
            {
              "x": 1703.93,
              "y": 50246.9
            },
            {
              "x": 1702.95,
              "y": 50701.9
            },
            {
              "x": 1701.97,
              "y": 51075.4
            },
            {
              "x": 1700.99,
              "y": 51161.3
            }
          ],
          "color": "#ec4899"
        }
      ],
      "createdAt": "2024-11-17T12:51:28.535Z",
      "name": "aaabbb"
    }
  ]
}